.gitignore
README.md
setup.cfg
setup.py
printr/__init__.py
python_printr.egg-info/PKG-INFO
python_printr.egg-info/SOURCES.txt
python_printr.egg-info/dependency_links.txt
python_printr.egg-info/requires.txt
python_printr.egg-info/top_level.txt