Metadata-Version: 2.1
Name: python-printr
Version: 4.0
Summary: printr
Home-page: https://github.com/xjxckk/python-printr/
Download-URL: https://github.com/xjxckk/python-printr/archive/refs/tags/v0.1.tar.gz
